{
  "project_info": {
    "project_number": "130931728626",
    "firebase_url": "https://login-1e7df.firebaseio.com",
    "project_id": "login-1e7df",
    "storage_bucket": "login-1e7df.appspot.com"
  },
  "client": [
    {
      "client_info": {
        "mobilesdk_app_id": "1:130931728626:android:fca3ff56a414b8f05b306b",
        "android_client_info": {
          "package_name": "com.example.splashtrial"
        }
      },
      "oauth_client": [
        {
          "client_id": "130931728626-607b39jg4u11uark1fb13n0p23ojd2ps.apps.googleusercontent.com",
          "client_type": 3
        }
      ],
      "api_key": [
        {
          "current_key": "AIzaSyD2piUchLLDlXDaSuyJPkCYnHImXBJfbzk"
        }
      ],
      "services": {
        "appinvite_service": {
          "other_platform_oauth_client": [
            {
              "client_id": "130931728626-607b39jg4u11uark1fb13n0p23ojd2ps.apps.googleusercontent.com",
              "client_type": 3
            }
          ]
        }
      }
    }
  ],
  "configuration_version": "1"
}